agentic_ai/__init__.py
agentic_ai/app_context.py
agentic_ai/cli.py
agentic_ai/defaults.py
agentic_ai/ids.py
agentic_ai/prompt_loader.py
agentic_ai/py.typed
agentic_ai/system_prompt_provider.py
agentic_ai/ag_ui/__init__.py
agentic_ai/ag_ui/adapter.py
agentic_ai/ag_ui/server/__init__.py
agentic_ai/ag_ui/server/app.py
agentic_ai/ag_ui/server/cli.py
agentic_ai/ag_ui/server/middleware.py
agentic_ai/agent/__init__.py
agentic_ai/agent/core.py
agentic_ai/agent/declarative_builder.py
agentic_ai/agent/sub_agent.py
agentic_ai/artifacts/__init__.py
agentic_ai/artifacts/core.py
agentic_ai/config/__init__.py
agentic_ai/config/agent.py
agentic_ai/config/base.py
agentic_ai/config/loader.py
agentic_ai/config/manifest.py
agentic_ai/config/registry.py
agentic_ai/config/store.py
agentic_ai/llm/__init__.py
agentic_ai/llm/client.py
agentic_ai/llm/config.py
agentic_ai/llm/embedding.py
agentic_ai/llm/factory.py
agentic_ai/mcp/__init__.py
agentic_ai/mcp/client.py
agentic_ai/mcp/loader.py
agentic_ai/mcp/manifest.py
agentic_ai/mcp/tools.py
agentic_ai/middleware/__init__.py
agentic_ai/middleware/loader.py
agentic_ai/middleware/persistence.py
agentic_ai/observability/__init__.py
agentic_ai/observability/logging.py
agentic_ai/observability/setup.py
agentic_ai/observability/structured.py
agentic_ai/observability/tracing.py
agentic_ai/planning/__init__.py
agentic_ai/planning/core.py
agentic_ai/runtime/__init__.py
agentic_ai/runtime/bootstrap.py
agentic_ai/runtime/context.py
agentic_ai/runtime/context_compaction.py
agentic_ai/runtime/contexts.py
agentic_ai/runtime/session_builder.py
agentic_ai/runtime/session_factory.py
agentic_ai/runtime/tool_runtime.py
agentic_ai/tools/__init__.py
agentic_ai/tools/loader.py
agentic_ai/tools/manifest.py
agentic_ai/tools/provider.py
agentic_ai/workspace/__init__.py
agentic_ai/workspace/core.py
agentic_ai/workspace/middleware.py
agentic_ai_sdk-0.1.7.dist-info/METADATA
agentic_ai_sdk-0.1.7.dist-info/WHEEL
agentic_ai_sdk-0.1.7.dist-info/entry_points.txt
agentic_ai_sdk-0.1.7.dist-info/licenses/LICENSE
agentic_ai_sdk-0.1.7.dist-info/RECORD
