Metadata-Version: 2.4
Name: agentic-ai-sdk
Version: 0.1.7
Summary: SDK for building AI agent 2.0.
Author: Frank Lin
License-Expression: MIT
License-File: LICENSE
Keywords: agent,agentic,ai,framework,llm,sdk
Classifier: Development Status :: 4 - Beta
Classifier: Intended Audience :: Developers
Classifier: License :: OSI Approved :: MIT License
Classifier: Programming Language :: Python :: 3
Classifier: Topic :: Scientific/Engineering :: Artificial Intelligence
Requires-Python: <=3.14,>=3.11
Requires-Dist: agent-framework<1.1,>=1.0.0b251114
Requires-Dist: pydantic<3,>=2.7.0
Requires-Dist: pyyaml<7,>=6.0.0
Provides-Extra: ag-ui
Requires-Dist: ag-ui-protocol<0.2,>=0.1.10; extra == 'ag-ui'
Requires-Dist: agent-framework-ag-ui<1.1,>=1.0.0b251117; extra == 'ag-ui'
Provides-Extra: all
Requires-Dist: ag-ui-protocol<0.2,>=0.1.10; extra == 'all'
Requires-Dist: agent-framework-ag-ui<1.1,>=1.0.0b251117; extra == 'all'
Requires-Dist: opentelemetry-api<2,>=1.20.0; extra == 'all'
Requires-Dist: opentelemetry-exporter-otlp-proto-grpc<2,>=1.20.0; extra == 'all'
Requires-Dist: opentelemetry-sdk<2,>=1.20.0; extra == 'all'
Provides-Extra: dev
Requires-Dist: pytest-asyncio>=0.23.0; extra == 'dev'
Requires-Dist: pytest-cov>=4.1.0; extra == 'dev'
Requires-Dist: pytest>=8.3.0; extra == 'dev'
Provides-Extra: observability
Requires-Dist: opentelemetry-api<2,>=1.20.0; extra == 'observability'
Requires-Dist: opentelemetry-exporter-otlp-proto-grpc<2,>=1.20.0; extra == 'observability'
Requires-Dist: opentelemetry-sdk<2,>=1.20.0; extra == 'observability'
